<edmx:Edmx Version="1.0" xmlns:edmx="http://schemas.microsoft.com/ado/2007/06/edmx"                                                                                                                                                                            
	xmlns:m="http://schemas.microsoft.com/ado/2007/08/dataservices/metadata" xmlns:sap="http://www.sap.com/Protocols/SAPData">                                                                                                                                    
	<edmx:Reference                                                                                                                                                                                                                                               
		Uri="http://sap/opu/odata/IWFND/CATALOGSERVICE;v=2/Vocabularies(TechnicalName='%2FIWBEP%2FVOC_COMMON',Version='0001',SAP__Origin='LOCAL')/$value"                                                                                                            
		xmlns:edmx="http://docs.oasis-open.org/odata/ns/edmx"><edmx:Include Namespace="com.sap.vocabularies.Common.v1" Alias="Common"/></edmx:Reference>                                                                                                             
	<edmx:Reference                                                                                                                                                                                                                                               
		Uri="http://sap/opu/odata/IWFND/CATALOGSERVICE;v=2/Vocabularies(TechnicalName='%2FIWBEP%2FVOC_CAPABILITIES',Version='0001',SAP__Origin='LOCAL')/$value"                                                                                                      
		xmlns:edmx="http://docs.oasis-open.org/odata/ns/edmx"><edmx:Include Namespace="Org.OData.Capabilities.V1" Alias="Capabilities"/></edmx:Reference>                                                                                                            
	<edmx:Reference                                                                                                                                                                                                                                               
		Uri="http://sap/opu/odata/IWFND/CATALOGSERVICE;v=2/Vocabularies(TechnicalName='%2FIWBEP%2FVOC_COMMUNICATION',Version='0001',SAP__Origin='LOCAL')/$value"                                                                                                     
		xmlns:edmx="http://docs.oasis-open.org/odata/ns/edmx"><edmx:Include Namespace="com.sap.vocabularies.Communication.v1" Alias="Communication"/></edmx:Reference>                                                                                               
	<edmx:DataServices m:DataServiceVersion="2.0">                                                                                                                                                                                                                
		<Schema Namespace="ZIM_C_ESTADIOS_BOPF_CDS" xml:lang="en" sap:schema-version="1" xmlns="http://schemas.microsoft.com/ado/2008/09/edm">                                                                                                                       
			<EntityType Name="ZIM_C_ESTADIOS_BOPFType" sap:label="Estadios,public view,VDM cons view" sap:content-version="1">                                                                                                                                          
				<Key><PropertyRef Name="id_estadio"/></Key><Property Name="id_estadio" Type="Edm.String" Nullable="false" MaxLength="3" sap:display-format="NonNegative" sap:label="ID do Estádio"                                                                         
					sap:quickinfo="ID dos clubes"/><Property Name="NomeEstadio" Type="Edm.String" MaxLength="72" sap:display-format="UpperCase" sap:label="Nome do Estádio"                                                                                                   
					sap:quickinfo="Fundado em"/><Property Name="Capacidade" Type="Edm.Int32" sap:label="Capacidade" sap:quickinfo="Capacidade do Estádio"/><NavigationProperty Name="to_Clubes" Relationship="ZIM_C_ESTADIOS_BOPF_CDS.assoc_CB872505B0B5850E64735654AAAB902B" 
					FromRole="FromRole_assoc_CB872505B0B5850E64735654AAAB902B" ToRole="ToRole_assoc_CB872505B0B5850E64735654AAAB902B"/><NavigationProperty Name="to_Partidas" Relationship="ZIM_C_ESTADIOS_BOPF_CDS.assoc_4D502C4F674D5312CBC15C9CD12D2565"                   
					FromRole="FromRole_assoc_4D502C4F674D5312CBC15C9CD12D2565" ToRole="ToRole_assoc_4D502C4F674D5312CBC15C9CD12D2565"/></EntityType>                                                                                                                          
			<EntityType Name="ZIM_I_CLUBES_BOPFType" sap:label="Clubes, private view, VDM interface view" sap:content-version="1">                                                                                                                                      
				<Key><PropertyRef Name="id_clube"/><PropertyRef Name="id_estadio"/></Key><Property Name="id_clube" Type="Edm.String" Nullable="false" MaxLength="3" sap:display-format="NonNegative" sap:label="ID"                                                        
					sap:quickinfo="ID dos clubes"/><Property Name="id_estadio" Type="Edm.String" Nullable="false" MaxLength="3" sap:display-format="NonNegative" sap:label="ID"                                                                                               
					sap:quickinfo="ID dos clubes"/><Property Name="NomeTime" Type="Edm.String" MaxLength="35" sap:display-format="UpperCase" sap:label="Nome" sap:quickinfo="Nome do Time"/><Property Name="NomeCompleto" Type="Edm.String" MaxLength="72" sap:display-format+
="UpperCase" sap:label="Nome Completo"                                                                                                                                                                                                                         
					sap:quickinfo="Nome Completo do Clube"/><Property Name="Fundacao" Type="Edm.DateTime" Precision="0" sap:display-format="Date" sap:label="Fundado em"/><Property Name="Tecnico" Type="Edm.String" MaxLength="72" sap:display-format="UpperCase" sap:label=+
"Nome do Técnico"/><Property Name="filename" Type="Edm.String" MaxLength="72" sap:display-format="UpperCase" sap:label="Logo File"                                                                                                                             
					sap:quickinfo="Arquivo do Logo do Time"/></EntityType>                                                                                                                                                                                                    
			<EntityType Name="ZIM_I_ESTADIOS_BOPFType" sap:label="Estadios, private view, VDM interf view" sap:content-version="1">                                                                                                                                     
				<Key><PropertyRef Name="id_estadio"/></Key><Property Name="id_estadio" Type="Edm.String" Nullable="false" MaxLength="3" sap:display-format="NonNegative" sap:label="ID"                                                                                    
					sap:quickinfo="ID dos clubes"/><Property Name="NomeEstadio" Type="Edm.String" MaxLength="72" sap:display-format="UpperCase" sap:label="Nome do Estádio"                                                                                                   
					sap:quickinfo="Fundado em"/><Property Name="Capacidade" Type="Edm.Int32" sap:label="Capacidade" sap:quickinfo="Capacidade do Estádio"/></EntityType>                                                                                                      
			<EntityType Name="ZIM_I_PARTIDAS_BOPFType" sap:label="Part., private view, VDM interface view" sap:content-version="1">                                                                                                                                     
				<Key><PropertyRef Name="id_rodada"/><PropertyRef Name="id_partida"/><PropertyRef Name="id_estadio"/><PropertyRef Name="id_time_a"/><PropertyRef Name="id_time_b"/></Key><Property Name="id_rodada" Type="Edm.String" Nullable="false" MaxLength="3" sap:di+
splay-format="NonNegative" sap:label="ID"                                                                                                                                                                                                                      
					sap:quickinfo="ID dos clubes"/><Property Name="id_partida" Type="Edm.String" Nullable="false" MaxLength="3" sap:display-format="NonNegative" sap:label="ID"                                                                                               
					sap:quickinfo="ID dos clubes"/><Property Name="id_estadio" Type="Edm.String" Nullable="false" MaxLength="3" sap:display-format="NonNegative" sap:label="ID"                                                                                               
					sap:quickinfo="ID dos clubes" sap:value-list="standard"/><Property Name="id_time_a" Type="Edm.String" Nullable="false" MaxLength="3" sap:display-format="NonNegative" sap:label="ID"                                                                      
					sap:quickinfo="ID dos clubes" sap:value-list="standard"/><Property Name="id_time_b" Type="Edm.String" Nullable="false" MaxLength="3" sap:display-format="NonNegative" sap:label="ID"                                                                      
					sap:quickinfo="ID dos clubes" sap:value-list="standard"/><Property Name="Data" Type="Edm.DateTime" Precision="0" sap:display-format="Date" sap:label="Date"/><Property Name="Publico" Type="Edm.Int32" sap:label="Público"/><Property Name="Renda" Type="+
Edm.Decimal" Precision="17" Scale="3" sap:unit="Moeda" sap:label="Renda"/><Property Name="Moeda" Type="Edm.String" MaxLength="5" sap:label="Currency Key" sap:semantics="currency-code"/><Property Name="Placar_Time_A" Type="Edm.Byte" sap:label="Placar"/><P+
roperty Name="Placar_Time_B" Type="Edm.Byte" sap:label="Placar"/><NavigationProperty Name="to_clube_A" Relationship="ZIM_C_ESTADIOS_BOPF_CDS.assoc_82EFD302E91BAA5412252F3B0D1B0E8D"                                                                           
					FromRole="FromRole_assoc_82EFD302E91BAA5412252F3B0D1B0E8D" ToRole="ToRole_assoc_82EFD302E91BAA5412252F3B0D1B0E8D"/><NavigationProperty Name="to_clube_B" Relationship="ZIM_C_ESTADIOS_BOPF_CDS.assoc_32CE612BD358C1BF442E6588610EB209"                    
					FromRole="FromRole_assoc_32CE612BD358C1BF442E6588610EB209" ToRole="ToRole_assoc_32CE612BD358C1BF442E6588610EB209"/><NavigationProperty Name="to_estadio" Relationship="ZIM_C_ESTADIOS_BOPF_CDS.assoc_A5B9F7EDA7A539397F5FAD267CC68918"                    
					FromRole="FromRole_assoc_A5B9F7EDA7A539397F5FAD267CC68918" ToRole="ToRole_assoc_A5B9F7EDA7A539397F5FAD267CC68918"/></EntityType>                                                                                                                          
			<Association Name="assoc_82EFD302E91BAA5412252F3B0D1B0E8D" sap:content-version="1"><End Type="ZIM_C_ESTADIOS_BOPF_CDS.ZIM_I_PARTIDAS_BOPFType" Multiplicity="1" Role="FromRole_assoc_82EFD302E91BAA5412252F3B0D1B0E8D"/><End Type="ZIM_C_ESTADIOS_BOPF_CDS.+
ZIM_I_CLUBES_BOPFType" Multiplicity="1" Role="ToRole_assoc_82EFD302E91BAA5412252F3B0D1B0E8D"/></Association>                                                                                                                                                   
			<Association Name="assoc_32CE612BD358C1BF442E6588610EB209" sap:content-version="1"><End Type="ZIM_C_ESTADIOS_BOPF_CDS.ZIM_I_PARTIDAS_BOPFType" Multiplicity="1" Role="FromRole_assoc_32CE612BD358C1BF442E6588610EB209"/><End Type="ZIM_C_ESTADIOS_BOPF_CDS.+
ZIM_I_CLUBES_BOPFType" Multiplicity="1" Role="ToRole_assoc_32CE612BD358C1BF442E6588610EB209"/></Association>                                                                                                                                                   
			<Association Name="assoc_A5B9F7EDA7A539397F5FAD267CC68918" sap:content-version="1"><End Type="ZIM_C_ESTADIOS_BOPF_CDS.ZIM_I_PARTIDAS_BOPFType" Multiplicity="1" Role="FromRole_assoc_A5B9F7EDA7A539397F5FAD267CC68918"/><End Type="ZIM_C_ESTADIOS_BOPF_CDS.+
ZIM_I_ESTADIOS_BOPFType" Multiplicity="1" Role="ToRole_assoc_A5B9F7EDA7A539397F5FAD267CC68918"/>                                                                                                                                                               
				<ReferentialConstraint>                                                                                                                                                                                                                                    
					<Principal Role="ToRole_assoc_A5B9F7EDA7A539397F5FAD267CC68918"><PropertyRef Name="id_estadio"/></Principal>                                                                                                                                              
					<Dependent Role="FromRole_assoc_A5B9F7EDA7A539397F5FAD267CC68918"><PropertyRef Name="id_estadio"/></Dependent>                                                                                                                                            
				</ReferentialConstraint>                                                                                                                                                                                                                                   
			</Association>                                                                                                                                                                                                                                              
			<Association Name="assoc_4D502C4F674D5312CBC15C9CD12D2565" sap:content-version="1"><End Type="ZIM_C_ESTADIOS_BOPF_CDS.ZIM_C_ESTADIOS_BOPFType" Multiplicity="1" Role="FromRole_assoc_4D502C4F674D5312CBC15C9CD12D2565"/><End Type="ZIM_C_ESTADIOS_BOPF_CDS.+
ZIM_I_PARTIDAS_BOPFType" Multiplicity="*" Role="ToRole_assoc_4D502C4F674D5312CBC15C9CD12D2565"/></Association>                                                                                                                                                 
			<Association Name="assoc_CB872505B0B5850E64735654AAAB902B" sap:content-version="1"><End Type="ZIM_C_ESTADIOS_BOPF_CDS.ZIM_C_ESTADIOS_BOPFType" Multiplicity="1" Role="FromRole_assoc_CB872505B0B5850E64735654AAAB902B"/><End Type="ZIM_C_ESTADIOS_BOPF_CDS.+
ZIM_I_CLUBES_BOPFType" Multiplicity="0..1" Role="ToRole_assoc_CB872505B0B5850E64735654AAAB902B"/></Association>                                                                                                                                                
			<EntityContainer Name="ZIM_C_ESTADIOS_BOPF_CDS_Entities" m:IsDefaultEntityContainer="true" sap:supported-formats="atom json xlsx"><EntitySet Name="ZIM_C_ESTADIOS_BOPF" EntityType="ZIM_C_ESTADIOS_BOPF_CDS.ZIM_C_ESTADIOS_BOPFType" sap:content-version="1+
"/><EntitySet Name="ZIM_I_CLUBES_BOPF" EntityType="ZIM_C_ESTADIOS_BOPF_CDS.ZIM_I_CLUBES_BOPFType" sap:content-version="1"/><EntitySet Name="ZIM_I_ESTADIOS_BOPF" EntityType="ZIM_C_ESTADIOS_BOPF_CDS.ZIM_I_ESTADIOS_BOPFType" sap:content-version="1"/><Entity+
Set Name="ZIM_I_PARTIDAS_BOPF" EntityType="ZIM_C_ESTADIOS_BOPF_CDS.ZIM_I_PARTIDAS_BOPFType" sap:content-version="1"/>                                                                                                                                          
				<AssociationSet Name="assoc_4D502C4F674D5312CBC15C9CD12D2565" Association="ZIM_C_ESTADIOS_BOPF_CDS.assoc_4D502C4F674D5312CBC15C9CD12D2565"                                                                                                                 
					sap:creatable="false" sap:updatable="false" sap:deletable="false" sap:content-version="1"><End EntitySet="ZIM_C_ESTADIOS_BOPF" Role="FromRole_assoc_4D502C4F674D5312CBC15C9CD12D2565"/><End EntitySet="ZIM_I_PARTIDAS_BOPF" Role="ToRole_assoc_4D502C4F67+
4D5312CBC15C9CD12D2565"/></AssociationSet>                                                                                                                                                                                                                     
				<AssociationSet Name="assoc_A5B9F7EDA7A539397F5FAD267CC68918" Association="ZIM_C_ESTADIOS_BOPF_CDS.assoc_A5B9F7EDA7A539397F5FAD267CC68918"                                                                                                                 
					sap:creatable="false" sap:updatable="false" sap:deletable="false" sap:content-version="1"><End EntitySet="ZIM_I_PARTIDAS_BOPF" Role="FromRole_assoc_A5B9F7EDA7A539397F5FAD267CC68918"/><End EntitySet="ZIM_I_ESTADIOS_BOPF" Role="ToRole_assoc_A5B9F7EDA7+
A539397F5FAD267CC68918"/></AssociationSet>                                                                                                                                                                                                                     
				<AssociationSet Name="assoc_CB872505B0B5850E64735654AAAB902B" Association="ZIM_C_ESTADIOS_BOPF_CDS.assoc_CB872505B0B5850E64735654AAAB902B"                                                                                                                 
					sap:creatable="false" sap:updatable="false" sap:deletable="false" sap:content-version="1"><End EntitySet="ZIM_C_ESTADIOS_BOPF" Role="FromRole_assoc_CB872505B0B5850E64735654AAAB902B"/><End EntitySet="ZIM_I_CLUBES_BOPF" Role="ToRole_assoc_CB872505B0B5+
850E64735654AAAB902B"/></AssociationSet>                                                                                                                                                                                                                       
				<AssociationSet Name="assoc_82EFD302E91BAA5412252F3B0D1B0E8D" Association="ZIM_C_ESTADIOS_BOPF_CDS.assoc_82EFD302E91BAA5412252F3B0D1B0E8D"                                                                                                                 
					sap:creatable="false" sap:updatable="false" sap:deletable="false" sap:content-version="1"><End EntitySet="ZIM_I_PARTIDAS_BOPF" Role="FromRole_assoc_82EFD302E91BAA5412252F3B0D1B0E8D"/><End EntitySet="ZIM_I_CLUBES_BOPF" Role="ToRole_assoc_82EFD302E91B+
AA5412252F3B0D1B0E8D"/></AssociationSet>                                                                                                                                                                                                                       
				<AssociationSet Name="assoc_32CE612BD358C1BF442E6588610EB209" Association="ZIM_C_ESTADIOS_BOPF_CDS.assoc_32CE612BD358C1BF442E6588610EB209"                                                                                                                 
					sap:creatable="false" sap:updatable="false" sap:deletable="false" sap:content-version="1"><End EntitySet="ZIM_I_PARTIDAS_BOPF" Role="FromRole_assoc_32CE612BD358C1BF442E6588610EB209"/><End EntitySet="ZIM_I_CLUBES_BOPF" Role="ToRole_assoc_32CE612BD358+
C1BF442E6588610EB209"/></AssociationSet>                                                                                                                                                                                                                       
			</EntityContainer>                                                                                                                                                                                                                                          
			<Annotations Target="ZIM_C_ESTADIOS_BOPF_CDS.ZIM_I_PARTIDAS_BOPFType/id_estadio" xmlns="http://docs.oasis-open.org/odata/ns/edm">                                                                                                                           
				<Annotation Term="Common.ValueList">                                                                                                                                                                                                                       
					<Record><PropertyValue Property="Label" String="Estadios, private view, VDM interf view"/><PropertyValue Property="CollectionPath" String="ZIM_I_ESTADIOS_BOPF"/><PropertyValue Property="SearchSupported" Bool="false"/>                                 
						<PropertyValue Property="Parameters">                                                                                                                                                                                                                    
							<Collection>                                                                                                                                                                                                                                            
								<Record Type="Common.ValueListParameterInOut"><PropertyValue Property="LocalDataProperty" PropertyPath="id_estadio"/><PropertyValue Property="ValueListProperty" String="id_estadio"/></Record>                                                        
							</Collection>                                                                                                                                                                                                                                           
						</PropertyValue>                                                                                                                                                                                                                                         
					</Record>                                                                                                                                                                                                                                                 
				</Annotation>                                                                                                                                                                                                                                              
			</Annotations>                                                                                                                                                                                                                                              
			<Annotations Target="ZIM_C_ESTADIOS_BOPF_CDS.ZIM_I_PARTIDAS_BOPFType/id_time_a" xmlns="http://docs.oasis-open.org/odata/ns/edm">                                                                                                                            
				<Annotation Term="Common.ValueList">                                                                                                                                                                                                                       
					<Record><PropertyValue Property="Label" String="Clubes, private view, VDM interface view"/><PropertyValue Property="CollectionPath" String="ZIM_I_CLUBES_BOPF"/><PropertyValue Property="SearchSupported" Bool="false"/>                                  
						<PropertyValue Property="Parameters">                                                                                                                                                                                                                    
							<Collection>                                                                                                                                                                                                                                            
								<Record Type="Common.ValueListParameterInOut"><PropertyValue Property="LocalDataProperty" PropertyPath="id_time_a"/><PropertyValue Property="ValueListProperty" String="id_clube"/></Record>                                                           
							</Collection>                                                                                                                                                                                                                                           
						</PropertyValue>                                                                                                                                                                                                                                         
					</Record>                                                                                                                                                                                                                                                 
				</Annotation>                                                                                                                                                                                                                                              
			</Annotations>                                                                                                                                                                                                                                              
			<Annotations Target="ZIM_C_ESTADIOS_BOPF_CDS.ZIM_I_PARTIDAS_BOPFType/id_time_b" xmlns="http://docs.oasis-open.org/odata/ns/edm">                                                                                                                            
				<Annotation Term="Common.ValueList">                                                                                                                                                                                                                       
					<Record><PropertyValue Property="Label" String="Clubes, private view, VDM interface view"/><PropertyValue Property="CollectionPath" String="ZIM_I_CLUBES_BOPF"/><PropertyValue Property="SearchSupported" Bool="false"/>                                  
						<PropertyValue Property="Parameters">                                                                                                                                                                                                                    
							<Collection>                                                                                                                                                                                                                                            
								<Record Type="Common.ValueListParameterInOut"><PropertyValue Property="LocalDataProperty" PropertyPath="id_time_b"/><PropertyValue Property="ValueListProperty" String="id_clube"/></Record>                                                           
							</Collection>                                                                                                                                                                                                                                           
						</PropertyValue>                                                                                                                                                                                                                                         
					</Record>                                                                                                                                                                                                                                                 
				</Annotation>                                                                                                                                                                                                                                              
			</Annotations>                                                                                                                                                                                                                                              
			<Annotations Target="ZIM_C_ESTADIOS_BOPF_CDS.ZIM_C_ESTADIOS_BOPFType" xmlns="http://docs.oasis-open.org/odata/ns/edm">                                                                                                                                      
				<Annotation Term="Common.SemanticKey">                                                                                                                                                                                                                     
					<Collection>                                                                                                                                                                                                                                              
						<PropertyPath>id_estadio</PropertyPath>                                                                                                                                                                                                                  
					</Collection>                                                                                                                                                                                                                                             
				</Annotation>                                                                                                                                                                                                                                              
			</Annotations>                                                                                                                                                                                                                                              
			<Annotations Target="ZIM_C_ESTADIOS_BOPF_CDS.ZIM_I_CLUBES_BOPFType" xmlns="http://docs.oasis-open.org/odata/ns/edm">                                                                                                                                        
				<Annotation Term="Common.SemanticKey">                                                                                                                                                                                                                     
					<Collection>                                                                                                                                                                                                                                              
						<PropertyPath>id_estadio</PropertyPath>                                                                                                                                                                                                                  
						<PropertyPath>id_clube</PropertyPath>                                                                                                                                                                                                                    
					</Collection>                                                                                                                                                                                                                                             
				</Annotation>                                                                                                                                                                                                                                              
			</Annotations>                                                                                                                                                                                                                                              
			<Annotations Target="ZIM_C_ESTADIOS_BOPF_CDS.ZIM_I_ESTADIOS_BOPFType" xmlns="http://docs.oasis-open.org/odata/ns/edm">                                                                                                                                      
				<Annotation Term="Common.SemanticKey">                                                                                                                                                                                                                     
					<Collection>                                                                                                                                                                                                                                              
						<PropertyPath>id_estadio</PropertyPath>                                                                                                                                                                                                                  
					</Collection>                                                                                                                                                                                                                                             
				</Annotation>                                                                                                                                                                                                                                              
			</Annotations>                                                                                                                                                                                                                                              
			<Annotations Target="ZIM_C_ESTADIOS_BOPF_CDS.ZIM_I_PARTIDAS_BOPFType" xmlns="http://docs.oasis-open.org/odata/ns/edm">                                                                                                                                      
				<Annotation Term="Common.SemanticKey">                                                                                                                                                                                                                     
					<Collection>                                                                                                                                                                                                                                              
						<PropertyPath>id_partida</PropertyPath>                                                                                                                                                                                                                  
						<PropertyPath>id_rodada</PropertyPath>                                                                                                                                                                                                                   
					</Collection>                                                                                                                                                                                                                                             
				</Annotation>                                                                                                                                                                                                                                              
			</Annotations><atom:link rel="self" href="./sap/ZIM_C_ESTADIOS_BOPF_CDS/$metadata" xmlns:atom="http://www.w3.org/2005/Atom"/><atom:link rel="latest-version" href="./sap/ZIM_C_ESTADIOS_BOPF_CDS/$metadata" xmlns:atom="http://www.w3.org/2005/Atom"/></Sch+
ema>                                                                                                                                                                                                                                                           
	</edmx:DataServices>                                                                                                                                                                                                                                          
</edmx:Edmx>                                                                                                                                                                                                                                                   